decotools/__init__.py
decotools/applier.py
decotools/builtins.py
decotools/collections.py
decotools/itertools.py
pydecotools-0.2.2.dist-info/LICENSE
pydecotools-0.2.2.dist-info/METADATA
pydecotools-0.2.2.dist-info/WHEEL
pydecotools-0.2.2.dist-info/RECORD
