Metadata-Version: 2.1
Name: pydecotools
Version: 0.2.2
Summary: The collection of decorator utilities.
License: MIT
Keywords: decorator
Author: ilotoki0804
Author-email: ilotoki0804@gmail.com
Requires-Python: >=3.12,<4.0
Classifier: Development Status :: 1 - Planning
Classifier: Intended Audience :: Developers
Classifier: License :: OSI Approved :: MIT License
Classifier: Operating System :: OS Independent
Classifier: Programming Language :: Python :: 3
Classifier: Programming Language :: Python :: 3.12
Project-URL: Changelog, https://github.com/ilotoki0804/pydecotools#relese-note
Project-URL: Documentation, https://github.com/ilotoki0804/pydecotools
Project-URL: Homepage, https://ilotoki0804.gitbook.io/pydecotools/
Project-URL: Issues, https://github.com/ilotoki0804/pydecotools/issues
Project-URL: Repository, https://github.com/ilotoki0804/pydecotools
